DjangoRangeMiddleware/VERSION
DjangoRangeMiddleware/__init__.py
DjangoRangeMiddleware/middleware.py
DjangoRangeMiddleware/version.py
DjangoRangeMiddleware-1.0.1.dist-info/LICENSE.md
DjangoRangeMiddleware-1.0.1.dist-info/METADATA
DjangoRangeMiddleware-1.0.1.dist-info/WHEEL
DjangoRangeMiddleware-1.0.1.dist-info/top_level.txt
DjangoRangeMiddleware-1.0.1.dist-info/RECORD
