Metadata-Version: 2.1
Name: DjangoRangeMiddleware
Version: 1.0.1
Summary: Django Range Middleware
Home-page: https://github.com/QuackCoding/DjangoRangeMiddleware
Author: Aiden (Dev)
Author-email: 
Keywords: python,middleware,django,DjangoRangeMiddleware,Range
Classifier: Development Status :: 5 - Production/Stable
Classifier: Intended Audience :: Developers
Classifier: Programming Language :: Python :: 3
Classifier: Operating System :: Unix
Classifier: Operating System :: MacOS :: MacOS X
Classifier: Operating System :: Microsoft :: Windows
License-File: LICENSE.md
